[
  {
    "volume": "17 ETH",
    "volume change": "+27%",
    "rank": "8",
    "owners": "2534",
    "collection": "DeGods",
    "items": "8955",
    "sales": "5",
    "floor price": "3.53 ETH"
  },
  {
    "volume": "7 ETH",
    "volume change": "+73%",
    "rank": "12",
    "owners": "7496",
    "collection": "Lil Pudgys",
    "items": "21469",
    "sales": "7",
    "floor price": "1.03 ETH"
  },
  {
    "volume": "5 ETH",
    "volume change": "+530%",
    "rank": "16",
    "owners": "883",
    "collection": "Bit Bears by Berachain",
    "items": "2264",
    "sales": "2",
    "floor price": "2.65 ETH"
  },
  {
    "volume": "4 ETH",
    "volume change": "+407%",
    "rank": "18",
    "owners": "1179",
    "collection": "Neo Tokyo Outer Citizens",
    "items": "3279",
    "sales": "2",
    "floor price": "2.40 ETH"
  },
  {
    "volume": "4 ETH",
    "volume change": "-75%",
    "rank": "20",
    "owners": "1327",
    "collection": "Oh Ottie!",
    "items": "2000",
    "sales": "2",
    "floor price": "2.08 ETH"
  },
  {
    "volume": "4 ETH",
    "volume change": "+384%",
    "rank": "21",
    "owners": "2008",
    "collection": "Pixels - Farm Land",
    "items": "5000",
    "sales": "2",
    "floor price": "1.94 ETH"
  },
  {
    "volume": "4 ETH",
    "volume change": "+393%",
    "rank": "19",
    "owners": "5485",
    "collection": "Doodles Original Collection",
    "items": "9998",
    "sales": "2",
    "floor price": "2.10 ETH"
  },
  {
    "volume": "4 ETH",
    "volume change": "+422%",
    "rank": "17",
    "owners": "132",
    "collection": "Signature by Jack Butcher",
    "items": "200",
    "sales": "2",
    "floor price": "1.98 ETH"
  },
  {
    "volume": "6 ETH",
    "volume change": "+572%",
    "rank": "14",
    "owners": "5012",
    "collection": "Azuki Elementals",
    "items": "14801",
    "sales": "9",
    "floor price": "0.57 ETH"
  },
  {
    "volume": "6 ETH",
    "volume change": "+431%",
    "rank": "15",
    "owners": "15583",
    "collection": "Otherdeed for Otherside",
    "items": "46921",
    "sales": "11",
    "floor price": "0.52 ETH"
  },
  {
    "volume": "6 ETH",
    "volume change": "0",
    "rank": "13",
    "owners": "248",
    "collection": "NFTrees",
    "items": "421",
    "sales": "1",
    "floor price": "9.16 ETH"
  },
  {
    "volume": "8 ETH",
    "volume change": "+187%",
    "rank": "10",
    "owners": "1185",
    "collection": "Shishi",
    "items": "3520",
    "sales": "114",
    "floor price": "0.07 ETH"
  },
  {
    "volume": "8 ETH",
    "volume change": "+200%",
    "rank": "11",
    "owners": "3430",
    "collection": "Milady Maker",
    "items": "9732",
    "sales": "3",
    "floor price": "2.99 ETH"
  },
  {
    "volume": "14 ETH",
    "volume change": "-6%",
    "rank": "9",
    "owners": "2590",
    "collection": "Pixelmon - Generation 1",
    "items": "12292",
    "sales": "9",
    "floor price": "1.58 ETH"
  },
  {
    "volume": "63 ETH",
    "volume change": "+296%",
    "rank": "4",
    "owners": "2101",
    "collection": "Mocaverse",
    "items": "8888",
    "sales": "15",
    "floor price": "4.20 ETH"
  },
  {
    "volume": "38 ETH",
    "volume change": "+1,112%",
    "rank": "6",
    "owners": "2364",
    "collection": "Redacted Remilio Babies",
    "items": "9172",
    "sales": "62",
    "floor price": "0.65 ETH"
  },
  {
    "volume": "22 ETH",
    "volume change": "+2,218%",
    "rank": "7",
    "owners": "300",
    "collection": "AltLayer OG Badge NFT",
    "items": "400",
    "sales": "3",
    "floor price": "7.50 ETH"
  },
  {
    "volume": "40 ETH",
    "volume change": "+3,252%",
    "rank": "5",
    "owners": "4514",
    "collection": "y00ts",
    "items": "11576",
    "sales": "68",
    "floor price": "0.62 ETH"
  },
  {
    "volume": "109 ETH",
    "volume change": "-44%",
    "rank": "2",
    "owners": "11149",
    "collection": "Mutant Ape Yacht Club",
    "items": "19487",
    "sales": "22",
    "floor price": "5.05 ETH"
  },
  {
    "volume": "106 ETH",
    "volume change": "-41%",
    "rank": "3",
    "owners": "4345",
    "collection": "Pudgy Penguins",
    "items": "8888",
    "sales": "10",
    "floor price": "10.94 ETH"
  },
  {
    "volume": "325 ETH",
    "volume change": "+284%",
    "rank": "1",
    "owners": "4111",
    "collection": "Azuki",
    "items": "10000",
    "sales": "54",
    "floor price": "6.38 ETH"
  },
  {
    "volume": "4 ETH",
    "volume change": "+376%",
    "rank": "22",
    "owners": "432",
    "collection": "The Band Bears",
    "items": "1153",
    "sales": "1",
    "floor price": "3.76 ETH"
  },
  {
    "volume": "3 ETH",
    "volume change": "+57%",
    "rank": "23",
    "owners": "1041",
    "collection": "The Grapes",
    "items": "3332",
    "sales": "3",
    "floor price": "1.38 ETH"
  },
  {
    "volume": "3 ETH",
    "volume change": "+319%",
    "rank": "24",
    "owners": "5378",
    "collection": "World of Women",
    "items": "10000",
    "sales": "2",
    "floor price": "1.28 ETH"
  },
  {
    "volume": "3 ETH",
    "volume change": "+92%",
    "rank": "28",
    "owners": "5748",
    "collection": "Moonbirds",
    "items": "10000",
    "sales": "2",
    "floor price": "1.34 ETH"
  },
  {
    "volume": "3 ETH",
    "volume change": "+122%",
    "rank": "30",
    "owners": "1972",
    "collection": "Terraforms by Mathcastles",
    "items": "9911",
    "sales": "2",
    "floor price": "1.25 ETH"
  },
  {
    "volume": "3 ETH",
    "volume change": "+250%",
    "rank": "31",
    "owners": "74",
    "collection": "Infinity Pass",
    "items": "111",
    "sales": "1",
    "floor price": "15 ETH"
  },
  {
    "volume": "2 ETH",
    "volume change": "+411%",
    "rank": "32",
    "owners": "1875",
    "collection": "Lasogette",
    "items": "7743",
    "sales": "49",
    "floor price": "0.07 ETH"
  },
  {
    "volume": "3 ETH",
    "volume change": "+254%",
    "rank": "29",
    "owners": "1253",
    "collection": "IO: Imaginary Ones",
    "items": "8888",
    "sales": "2",
    "floor price": "1.39 ETH"
  },
  {
    "volume": "3 ETH",
    "volume change": "+100%",
    "rank": "26",
    "owners": "3607",
    "collection": "0N1 Force",
    "items": "7775",
    "sales": "4",
    "floor price": "0.84 ETH"
  },
  {
    "volume": "3 ETH",
    "volume change": "+117%",
    "rank": "27",
    "owners": "3433",
    "collection": "rektguy",
    "items": "8813",
    "sales": "5",
    "floor price": "0.42 ETH"
  },
  {
    "volume": "3 ETH",
    "volume change": "+313%",
    "rank": "25",
    "owners": "695",
    "collection": "DeepBlack",
    "items": "3074",
    "sales": "3",
    "floor price": "0.95 ETH"
  },
  {
    "volume": "2 ETH",
    "volume change": "0",
    "rank": "36",
    "owners": "409",
    "collection": "COACHK - CLUB",
    "items": "0",
    "sales": "1",
    "floor price": "2.25 ETH"
  },
  {
    "volume": "2 ETH",
    "volume change": "-37%",
    "rank": "38",
    "owners": "273",
    "collection": "Mittamita",
    "items": "605",
    "sales": "3",
    "floor price": "0.65 ETH"
  },
  {
    "volume": "1 ETH",
    "volume change": "+132%",
    "rank": "39",
    "owners": "4108",
    "collection": "Opepen Edition",
    "items": "16000",
    "sales": "4",
    "floor price": "0.35 ETH"
  },
  {
    "volume": "1 ETH",
    "volume change": "-86%",
    "rank": "40",
    "owners": "9612",
    "collection": "CLONE X - X TAKASHI MURAKAMI",
    "items": "19520",
    "sales": "1",
    "floor price": "1.36 ETH"
  },
  {
    "volume": "2 ETH",
    "volume change": "+114%",
    "rank": "37",
    "owners": "3347",
    "collection": "Yogapetz",
    "items": "10092",
    "sales": "2",
    "floor price": "0.73 ETH"
  },
  {
    "volume": "2 ETH",
    "volume change": "+175%",
    "rank": "34",
    "owners": "1262",
    "collection": "Pixelmon Trainers - Generation 1",
    "items": "7000",
    "sales": "5",
    "floor price": "0.37 ETH"
  },
  {
    "volume": "2 ETH",
    "volume change": "-68%",
    "rank": "35",
    "owners": "2211",
    "collection": "Ultiverse - Electric Sheep",
    "items": "7000",
    "sales": "1",
    "floor price": "1.83 ETH"
  },
  {
    "volume": "2 ETH",
    "volume change": "-84%",
    "rank": "33",
    "owners": "2454",
    "collection": "Creepz by OVERLORD",
    "items": "9700",
    "sales": "1",
    "floor price": "2.65 ETH"
  },
  {
    "volume": "1 ETH",
    "volume change": "+1,157%",
    "rank": "44",
    "owners": "1728",
    "collection": "God Hates NFTees",
    "items": "5022",
    "sales": "10",
    "floor price": "0.11 ETH"
  },
  {
    "volume": "1 ETH",
    "volume change": "+112%",
    "rank": "46",
    "owners": "2843",
    "collection": "Pudgy Rods",
    "items": "7394",
    "sales": "2",
    "floor price": "0.59 ETH"
  },
  {
    "volume": "1 ETH",
    "volume change": "-0.95%",
    "rank": "47",
    "owners": "6553",
    "collection": "Meebits",
    "items": "19999",
    "sales": "1",
    "floor price": "1.11 ETH"
  },
  {
    "volume": "1 ETH",
    "volume change": "0",
    "rank": "48",
    "owners": "471",
    "collection": "The Bakery Genesis",
    "items": "1111",
    "sales": "2",
    "floor price": "0.55 ETH"
  },
  {
    "volume": "1 ETH",
    "volume change": "-74%",
    "rank": "45",
    "owners": "2471",
    "collection": "Loot (for Adventurers)",
    "items": "7779",
    "sales": "2",
    "floor price": "0.58 ETH"
  },
  {
    "volume": "1 ETH",
    "volume change": "+226%",
    "rank": "42",
    "owners": "785",
    "collection": "Chimpers",
    "items": "5555",
    "sales": "3",
    "floor price": "0.40 ETH"
  },
  {
    "volume": "1 ETH",
    "volume change": "+9%",
    "rank": "43",
    "owners": "747",
    "collection": "CALIVERSE Pioneer",
    "items": "5000",
    "sales": "8",
    "floor price": "0.15 ETH"
  },
  {
    "volume": "1 ETH",
    "volume change": "0",
    "rank": "41",
    "owners": "2348",
    "collection": "The Dev\u0027s NFT",
    "items": "7768",
    "sales": "39",
    "floor price": "0.04 ETH"
  },
  {
    "volume": "56 AVAX",
    "volume change": "+90%",
    "rank": "52",
    "owners": "844",
    "collection": "Dokyo",
    "items": "5555",
    "sales": "1",
    "floor price": "58 AVAX"
  },
  {
    "volume": "0.85 ETH",
    "volume change": "+85%",
    "rank": "54",
    "owners": "1918",
    "collection": "CyberKongz (Babies)",
    "items": "4000",
    "sales": "1",
    "floor price": "1.00 ETH"
  },
  {
    "volume": "0.85 ETH",
    "volume change": "+139%",
    "rank": "55",
    "owners": "60778",
    "collection": "Parallel Alpha",
    "items": "0",
    "sales": "1",
    "floor price": "\u003c 0.01 ETH"
  },
  {
    "volume": "0.85 ETH",
    "volume change": "+107%",
    "rank": "56",
    "owners": "1840",
    "collection": "Kubz",
    "items": "9999",
    "sales": "2",
    "floor price": "0.42 ETH"
  },
  {
    "volume": "0.87 ETH",
    "volume change": "+87%",
    "rank": "53",
    "owners": "508",
    "collection": "Bursted Bubbles by Deblock",
    "items": "1000",
    "sales": "2",
    "floor price": "0.48 ETH"
  },
  {
    "volume": "0.95 ETH",
    "volume change": "+95%",
    "rank": "50",
    "owners": "1685",
    "collection": "Quirkies Originals",
    "items": "5000",
    "sales": "1",
    "floor price": "0.93 ETH"
  },
  {
    "volume": "0.92 ETH",
    "volume change": "0",
    "rank": "51",
    "owners": "595",
    "collection": "Delabs Adventure Pass Official",
    "items": "3433",
    "sales": "6",
    "floor price": "0.17 ETH"
  },
  {
    "volume": "0.98 ETH",
    "volume change": "-74%",
    "rank": "49",
    "owners": "823",
    "collection": "WADE Friends \u0026 Family Official",
    "items": "2100",
    "sales": "1",
    "floor price": "1.11 ETH"
  },
  {
    "volume": "0.80 ETH",
    "volume change": "+55%",
    "rank": "60",
    "owners": "2973",
    "collection": "Shrapnel Operators Collection",
    "items": "10000",
    "sales": "3",
    "floor price": "0.28 ETH"
  },
  {
    "volume": "0.77 ETH",
    "volume change": "+543%",
    "rank": "62",
    "owners": "5001",
    "collection": "My Curio Cards",
    "items": "0",
    "sales": "2",
    "floor price": "0.12 ETH"
  },
  {
    "volume": "0.76 ETH",
    "volume change": "0",
    "rank": "63",
    "owners": "1034",
    "collection": "Rags to Richie by Alec Monopoly",
    "items": "3333",
    "sales": "1",
    "floor price": "0.04 ETH"
  },
  {
    "volume": "0.75 ETH",
    "volume change": "+75%",
    "rank": "64",
    "owners": "2826",
    "collection": "OCM Karma",
    "items": "12763",
    "sales": "3",
    "floor price": "0.17 ETH"
  },
  {
    "volume": "0.80 ETH",
    "volume change": "+80%",
    "rank": "61",
    "owners": "176",
    "collection": "LOVE Tennis Art Project by Martin Grasser",
    "items": "300",
    "sales": "1",
    "floor price": "0.90 ETH"
  },
  {
    "volume": "0.82 ETH",
    "volume change": "0",
    "rank": "58",
    "owners": "2468",
    "collection": "Mavia Land",
    "items": "10000",
    "sales": "1",
    "floor price": "0.88 ETH"
  },
  {
    "volume": "0.81 ETH",
    "volume change": "+81%",
    "rank": "59",
    "owners": "1009",
    "collection": "Sugartown Oras by Zynga",
    "items": "6213",
    "sales": "2",
    "floor price": "0.42 ETH"
  },
  {
    "volume": "0.82 ETH",
    "volume change": "+0.60%",
    "rank": "57",
    "owners": "7525",
    "collection": "BEANZ Official",
    "items": "19950",
    "sales": "2",
    "floor price": "0.44 ETH"
  },
  {
    "volume": "0.65 ETH",
    "volume change": "+65%",
    "rank": "68",
    "owners": "1508",
    "collection": "Azra Games - The Hopeful",
    "items": "5555",
    "sales": "1",
    "floor price": "0.63 ETH"
  },
  {
    "volume": "0.59 ETH",
    "volume change": "+59%",
    "rank": "70",
    "owners": "282",
    "collection": "Trichro-matic by MountVitruvius",
    "items": "600",
    "sales": "1",
    "floor price": "0.76 ETH"
  },
  {
    "volume": "0.55 ETH",
    "volume change": "-40%",
    "rank": "71",
    "owners": "4178",
    "collection": "The Warlords of Champions Tactics",
    "items": "9998",
    "sales": "3",
    "floor price": "0.19 ETH"
  },
  {
    "volume": "0.55 ETH",
    "volume change": "0",
    "rank": "72",
    "owners": "1829",
    "collection": "Pixelady Maker",
    "items": "7997",
    "sales": "11",
    "floor price": "0.06 ETH"
  },
  {
    "volume": "0.63 ETH",
    "volume change": "+63%",
    "rank": "69",
    "owners": "2981",
    "collection": "Moonbirds: Mythics",
    "items": "8687",
    "sales": "6",
    "floor price": "0.13 ETH"
  },
  {
    "volume": "0.72 ETH",
    "volume change": "-79%",
    "rank": "66",
    "owners": "410",
    "collection": "Mocaverse Treasure Box - Lucky Neko",
    "items": "980",
    "sales": "1",
    "floor price": "0.49 ETH"
  },
  {
    "volume": "0.69 ETH",
    "volume change": "-9%",
    "rank": "67",
    "owners": "1011",
    "collection": "JeerGirl",
    "items": "2999",
    "sales": "3",
    "floor price": "0.27 ETH"
  },
  {
    "volume": "0.72 ETH",
    "volume change": "0",
    "rank": "65",
    "owners": "1053",
    "collection": "Looki",
    "items": "8732",
    "sales": "3",
    "floor price": "0.23 ETH"
  },
  {
    "volume": "0.48 ETH",
    "volume change": "0",
    "rank": "76",
    "owners": "379",
    "collection": "Threads by Professor Jun",
    "items": "777",
    "sales": "10",
    "floor price": "0.05 ETH"
  },
  {
    "volume": "0.47 ETH",
    "volume change": "+223%",
    "rank": "78",
    "owners": "4829",
    "collection": "Lazy Lions",
    "items": "10079",
    "sales": "3",
    "floor price": "0.17 ETH"
  },
  {
    "volume": "0.46 ETH",
    "volume change": "-27%",
    "rank": "79",
    "owners": "1811",
    "collection": "Balthazar raW Pass",
    "items": "5554",
    "sales": "3",
    "floor price": "0.16 ETH"
  },
  {
    "volume": "0.46 ETH",
    "volume change": "+46%",
    "rank": "80",
    "owners": "1220",
    "collection": "Sofa Vision",
    "items": "4590",
    "sales": "9",
    "floor price": "0.06 ETH"
  },
  {
    "volume": "0.47 ETH",
    "volume change": "0",
    "rank": "77",
    "owners": "320",
    "collection": "tiny based frogs",
    "items": "999",
    "sales": "2",
    "floor price": "0.19 ETH"
  },
  {
    "volume": "0.51 ETH",
    "volume change": "0",
    "rank": "74",
    "owners": "1614",
    "collection": "Descendants of Smurfcat",
    "items": "3333",
    "sales": "10",
    "floor price": "0.06 ETH"
  },
  {
    "volume": "0.50 ETH",
    "volume change": "-37%",
    "rank": "75",
    "owners": "13127",
    "collection": "Otherdeed Expanded",
    "items": "53078",
    "sales": "1",
    "floor price": "0.31 ETH"
  },
  {
    "volume": "0.54 ETH",
    "volume change": "0",
    "rank": "73",
    "owners": "3380",
    "collection": "a KID called BEAST",
    "items": "9999",
    "sales": "2",
    "floor price": "0.27 ETH"
  },
  {
    "volume": "0.42 ETH",
    "volume change": "0",
    "rank": "84",
    "owners": "407",
    "collection": "Worthless Web3 Game Pass",
    "items": "726",
    "sales": "1",
    "floor price": "0.41 ETH"
  },
  {
    "volume": "0.39 ETH",
    "volume change": "0",
    "rank": "86",
    "owners": "1099",
    "collection": "The Senses x Reddit Collectible Avatars",
    "items": "1302",
    "sales": "3",
    "floor price": "0.14 ETH"
  },
  {
    "volume": "0.39 ETH",
    "volume change": "0",
    "rank": "87",
    "owners": "1570",
    "collection": "SuperCreators - Gen Z",
    "items": "5555",
    "sales": "1",
    "floor price": "0.39 ETH"
  },
  {
    "volume": "0.37 ETH",
    "volume change": "+37%",
    "rank": "88",
    "owners": "1755",
    "collection": "Imaginary Rides",
    "items": "13888",
    "sales": "1",
    "floor price": "0.17 ETH"
  },
  {
    "volume": "0.39 ETH",
    "volume change": "+39%",
    "rank": "85",
    "owners": "1167",
    "collection": "Ether",
    "items": "4867",
    "sales": "3",
    "floor price": "0.15 ETH"
  },
  {
    "volume": "0.44 ETH",
    "volume change": "+44%",
    "rank": "82",
    "owners": "1710",
    "collection": "Skyborne - Genesis Immortals",
    "items": "9999",
    "sales": "3",
    "floor price": "0.12 ETH"
  },
  {
    "volume": "0.43 ETH",
    "volume change": "0",
    "rank": "83",
    "owners": "1818",
    "collection": "The Weirdo Ghost Gang",
    "items": "5556",
    "sales": "1",
    "floor price": "0.47 ETH"
  },
  {
    "volume": "0.46 ETH",
    "volume change": "+46%",
    "rank": "81",
    "owners": "6032",
    "collection": "alien frens",
    "items": "9998",
    "sales": "4",
    "floor price": "0.11 ETH"
  },
  {
    "volume": "0.34 ETH",
    "volume change": "0",
    "rank": "92",
    "owners": "5496",
    "collection": "Murakami.Flowers Official",
    "items": "10142",
    "sales": "1",
    "floor price": "0.33 ETH"
  },
  {
    "volume": "0.33 ETH",
    "volume change": "0",
    "rank": "94",
    "owners": "3523",
    "collection": "Invisible Friends",
    "items": "5000",
    "sales": "1",
    "floor price": "0.36 ETH"
  },
  {
    "volume": "0.32 ETH",
    "volume change": "+32%",
    "rank": "95",
    "owners": "24895",
    "collection": "The Sandbox",
    "items": "166217",
    "sales": "1",
    "floor price": "1,394 SAND"
  },
  {
    "volume": "20 AVAX",
    "volume change": "+32%",
    "rank": "96",
    "owners": "56",
    "collection": "STEAK.jpeg",
    "items": "100",
    "sales": "1",
    "floor price": "0"
  },
  {
    "volume": "0.33 ETH",
    "volume change": "+33%",
    "rank": "93",
    "owners": "839",
    "collection": "Spellborne Apartments",
    "items": "2902",
    "sales": "1",
    "floor price": "0.41 ETH"
  },
  {
    "volume": "0.36 ETH",
    "volume change": "+36%",
    "rank": "90",
    "owners": "6697",
    "collection": "RTFKT Animus Egg 🥚",
    "items": "16774",
    "sales": "1",
    "floor price": "0.39 ETH"
  },
  {
    "volume": "0.35 ETH",
    "volume change": "+85%",
    "rank": "91",
    "owners": "2139",
    "collection": "Edenhorde",
    "items": "8687",
    "sales": "2",
    "floor price": "0.22 ETH"
  },
  {
    "volume": "0.37 ETH",
    "volume change": "-1%",
    "rank": "89",
    "owners": "1922",
    "collection": "BlockGames Dice",
    "items": "5555",
    "sales": "1",
    "floor price": "0.38 ETH"
  },
  {
    "volume": "0.32 ETH",
    "volume change": "0",
    "rank": "98",
    "owners": "631",
    "collection": "Plasma Bears",
    "items": "1503",
    "sales": "4",
    "floor price": "0.12 ETH"
  },
  {
    "volume": "0.32 ETH",
    "volume change": "+32%",
    "rank": "99",
    "owners": "941",
    "collection": "Smoofs",
    "items": "8000",
    "sales": "5",
    "floor price": "149.90 MATIC"
  },
  {
    "volume": "0.31 ETH",
    "volume change": "-4%",
    "rank": "100",
    "owners": "2753",
    "collection": "Pirate Nation - Founder\u0027s Pirates",
    "items": "9999",
    "sales": "1",
    "floor price": "0.32 ETH"
  },
  {
    "volume": "0.32 ETH",
    "volume change": "0",
    "rank": "97",
    "owners": "5887",
    "collection": "The Seekers",
    "items": "37384",
    "sales": "1",
    "floor price": "0.04 ETH"
  }
]